{
  "targetSVG": "M9,0C4.029,0,0,4.029,0,9s4.029,9,9,9s9-4.029,9-9S13.971,0,9,0z M9,15.93 c-3.83,0-6.93-3.1-6.93-6.93S5.17,2.07,9,2.07s6.93,3.1,6.93,6.93S12.83,15.93,9,15.93 M12.5,9c0,1.933-1.567,3.5-3.5,3.5S5.5,10.933,5.5,9S7.067,5.5,9,5.5 S12.5,7.067,12.5,9z",
  "latlong": {
    "AD":{
        "latitude": 42.5,
        "longitude": 1.5
    },
    "AE":{
        "latitude": 24,
        "longitude": 54
    },
    "AF":{
        "latitude": 33,
        "longitude": 65
    },
    "AG":{
        "latitude": 17.05,
        "longitude": -61.8
    },
    "AI":{
        "latitude": 18.25,
        "longitude": -63.1667
    },
    "AL":{
        "latitude": 41,
        "longitude": 20
    },
    "AM":{
        "latitude": 40,
        "longitude": 45
    },
    "AN":{
        "latitude": 12.25,
        "longitude": -68.75
    },
    "AO":{
        "latitude": -12.5,
        "longitude": 18.5
    },
    "AP":{
        "latitude": 35,
        "longitude": 105
    },
    "AQ":{
        "latitude": -90,
        "longitude": 0
    },
    "AR":{
        "latitude": -34,
        "longitude": -64
    },
    "AS":{
        "latitude": -14.3333,
        "longitude": -170
    },
    "AT":{
        "latitude": 47.3333,
        "longitude": 13.3333
    },
    "AU":{
        "latitude": -27,
        "longitude": 133
    },
    "AW":{
        "latitude": 12.5,
        "longitude": -69.9667
    },
    "AZ":{
        "latitude": 40.5,
        "longitude": 47.5
    },
    "BA":{
        "latitude": 44,
        "longitude": 18
    },
    "BB":{
        "latitude": 13.1667,
        "longitude": -59.5333
    },
    "BD":{
        "latitude": 24,
        "longitude": 90
    },
    "BE":{
        "latitude": 50.8333,
        "longitude": 4
    },
    "BF":{
        "latitude": 13,
        "longitude": -2
    },
    "BG":{
        "latitude": 43,
        "longitude": 25
    },
    "BH":{
        "latitude": 26,
        "longitude": 50.55
    },
    "BI":{
        "latitude": -3.5,
        "longitude": 30
    },
    "BJ":{
        "latitude": 9.5,
        "longitude": 2.25
    },
    "BM":{
        "latitude": 32.3333,
        "longitude": -64.75
    },
    "BN":{
        "latitude": 4.5,
        "longitude": 114.6667
    },
    "BO":{
        "latitude": -17,
        "longitude": -65
    },
    "BR":{
        "latitude": -10,
        "longitude": -55
    },
    "BS":{
        "latitude": 24.25,
        "longitude": -76
    },
    "BT":{
        "latitude": 27.5,
        "longitude": 90.5
    },
    "BV":{
        "latitude": -54.4333,
        "longitude": 3.4
    },
    "BW":{
        "latitude": -22,
        "longitude": 24
    },
    "BY":{
        "latitude": 53,
        "longitude": 28
    },
    "BZ":{
        "latitude": 17.25,
        "longitude": -88.75
    },
    "CA":{
        "latitude": 54,
        "longitude": -100
    },
    "CC":{
        "latitude": -12.5,
        "longitude": 96.8333
    },
    "CD":{
        "latitude": 0,
        "longitude": 25
    },
    "CF":{
        "latitude": 7,
        "longitude": 21
    },
    "CG":{
        "latitude": -1,
        "longitude": 15
    },
    "CH":{
        "latitude": 47,
        "longitude": 8
    },
    "CI":{
        "latitude": 8,
        "longitude": -5
    },
    "CK":{
        "latitude": -21.2333,
        "longitude": -159.7667
    },
    "CL":{
        "latitude": -30,
        "longitude": -71
    },
    "CM":{
        "latitude": 6,
        "longitude": 12
    },
    "CN":{
        "latitude": 35,
        "longitude": 105
    },
    "CO":{
        "latitude": 4,
        "longitude": -72
    },
    "CR":{
        "latitude": 10,
        "longitude": -84
    },
    "CU":{
        "latitude": 21.5,
        "longitude": -80
    },
    "CV":{
        "latitude": 16,
        "longitude": -24
    },
    "CX":{
        "latitude": -10.5,
        "longitude": 105.6667
    },
    "CY":{
        "latitude": 35,
        "longitude": 33
    },
    "CZ":{
        "latitude": 49.75,
        "longitude": 15.5
    },
    "DE":{
        "latitude": 51,
        "longitude": 9
    },
    "DJ":{
        "latitude": 11.5,
        "longitude": 43
    },
    "DK":{
        "latitude": 56,
        "longitude": 10
    },
    "DM":{
        "latitude": 15.4167,
        "longitude": -61.3333
    },
    "DO":{
        "latitude": 19,
        "longitude": -70.6667
    },
    "DZ":{
        "latitude": 28,
        "longitude": 3
    },
    "EC":{
        "latitude": -2,
        "longitude": -77.5
    },
    "EE":{
        "latitude": 59,
        "longitude": 26
    },
    "EG":{
        "latitude": 27,
        "longitude": 30
    },
    "EH":{
        "latitude": 24.5,
        "longitude": -13
    },
    "ER":{
        "latitude": 15,
        "longitude": 39
    },
    "ES":{
        "latitude": 40,
        "longitude": -4
    },
    "ET":{
        "latitude": 8,
        "longitude": 38
    },
    "EU":{
        "latitude": 47,
        "longitude": 8
    },
    "FI":{
        "latitude": 62,
        "longitude": 26
    },
    "FJ":{
        "latitude": -18,
        "longitude": 175
    },
    "FK":{
        "latitude": -51.75,
        "longitude": -59
    },
    "FM":{
        "latitude": 6.9167,
        "longitude": 158.25
    },
    "FO":{
        "latitude": 62,
        "longitude": -7
    },
    "FR":{
        "latitude": 46,
        "longitude": 2
    },
    "GA":{
        "latitude": -1,
        "longitude": 11.75
    },
    "GB":{
        "latitude": 54,
        "longitude": -2
    },
    "GD":{
        "latitude": 12.1167,
        "longitude": -61.6667
    },
    "GE":{
        "latitude": 42,
        "longitude": 43.5
    },
    "GF":{
        "latitude": 4,
        "longitude": -53
    },
    "GH":{
        "latitude": 8,
        "longitude": -2
    },
    "GI":{
        "latitude": 36.1833,
        "longitude": -5.3667
    },
    "GL":{
        "latitude": 72,
        "longitude": -40
    },
    "GM":{
        "latitude": 13.4667,
        "longitude": -16.5667
    },
    "GN":{
        "latitude": 11,
        "longitude": -10
    },
    "GP":{
        "latitude": 16.25,
        "longitude": -61.5833
    },
    "GQ":{
        "latitude": 2,
        "longitude": 10
    },
    "GR":{
        "latitude": 39,
        "longitude": 22
    },
    "GS":{
        "latitude": -54.5,
        "longitude": -37
    },
    "GT":{
        "latitude": 15.5,
        "longitude": -90.25
    },
    "GU":{
        "latitude": 13.4667,
        "longitude": 144.7833
    },
    "GW":{
        "latitude": 12,
        "longitude": -15
    },
    "GY":{
        "latitude": 5,
        "longitude": -59
    },
    "HK":{
        "latitude": 22.25,
        "longitude": 114.1667
    },
    "HM":{
        "latitude": -53.1,
        "longitude": 72.5167
    },
    "HN":{
        "latitude": 15,
        "longitude": -86.5
    },
    "HR":{
        "latitude": 45.1667,
        "longitude": 15.5
    },
    "HT":{
        "latitude": 19,
        "longitude": -72.4167
    },
    "HU":{
        "latitude": 47,
        "longitude": 20
    },
    "ID":{
        "latitude": -5,
        "longitude": 120
    },
    "IE":{
        "latitude": 53,
        "longitude": -8
    },
    "IL":{
        "latitude": 31.5,
        "longitude": 34.75
    },
    "IN":{
        "latitude": 20,
        "longitude": 77
    },
    "IO":{
        "latitude": -6,
        "longitude": 71.5
    },
    "IQ":{
        "latitude": 33,
        "longitude": 44
    },
    "IR":{
        "latitude": 32,
        "longitude": 53
    },
    "IS":{
        "latitude": 65,
        "longitude": -18
    },
    "IT":{
        "latitude": 42.8333,
        "longitude": 12.8333
    },
    "JM":{
        "latitude": 18.25,
        "longitude": -77.5
    },
    "JO":{
        "latitude": 31,
        "longitude": 36
    },
    "JP":{
        "latitude": 36,
        "longitude": 138
    },
    "KE":{
        "latitude": 1,
        "longitude": 38
    },
    "KG":{
        "latitude": 41,
        "longitude": 75
    },
    "KH":{
        "latitude": 13,
        "longitude": 105
    },
    "KI":{
        "latitude": 1.4167,
        "longitude": 173
    },
    "KM":{
        "latitude": -12.1667,
        "longitude": 44.25
    },
    "KN":{
        "latitude": 17.3333,
        "longitude": -62.75
    },
    "KP":{
        "latitude": 40,
        "longitude": 127
    },
    "KR":{
        "latitude": 37,
        "longitude": 127.5
    },
    "KW":{
        "latitude": 29.3375,
        "longitude": 47.6581
    },
    "KY":{
        "latitude": 19.5,
        "longitude": -80.5
    },
    "KZ":{
        "latitude": 48,
        "longitude": 68
    },
    "LA":{
        "latitude": 18,
        "longitude": 105
    },
    "LB":{
        "latitude": 33.8333,
        "longitude": 35.8333
    },
    "LC":{
        "latitude": 13.8833,
        "longitude": -61.1333
    },
    "LI":{
        "latitude": 47.1667,
        "longitude": 9.5333
    },
    "LK":{
        "latitude": 7,
        "longitude": 81
    },
    "LR":{
        "latitude": 6.5,
        "longitude": -9.5
    },
    "LS":{
        "latitude": -29.5,
        "longitude": 28.5
    },
    "LT":{
        "latitude": 55,
        "longitude": 24
    },
    "LU":{
        "latitude": 49.75,
        "longitude": 6
    },
    "LV":{
        "latitude": 57,
        "longitude": 25
    },
    "LY":{
        "latitude": 25,
        "longitude": 17
    },
    "MA":{
        "latitude": 32,
        "longitude": -5
    },
    "MC":{
        "latitude": 43.7333,
        "longitude": 7.4
    },
    "MD":{
        "latitude": 47,
        "longitude": 29
    },
    "ME":{
        "latitude": 42.5,
        "longitude": 19.4
    },
    "MG":{
        "latitude": -20,
        "longitude": 47
    },
    "MH":{
        "latitude": 9,
        "longitude": 168
    },
    "MK":{
        "latitude": 41.8333,
        "longitude": 22
    },
    "ML":{
        "latitude": 17,
        "longitude": -4
    },
    "MM":{
        "latitude": 22,
        "longitude": 98
    },
    "MN":{
        "latitude": 46,
        "longitude": 105
    },
    "MO":{
        "latitude": 22.1667,
        "longitude": 113.55
    },
    "MP":{
        "latitude": 15.2,
        "longitude": 145.75
    },
    "MQ":{
        "latitude": 14.6667,
        "longitude": -61
    },
    "MR":{
        "latitude": 20,
        "longitude": -12
    },
    "MS":{
        "latitude": 16.75,
        "longitude": -62.2
    },
    "MT":{
        "latitude": 35.8333,
        "longitude": 14.5833
    },
    "MU":{
        "latitude": -20.2833,
        "longitude": 57.55
    },
    "MV":{
        "latitude": 3.25,
        "longitude": 73
    },
    "MW":{
        "latitude": -13.5,
        "longitude": 34
    },
    "MX":{
        "latitude": 23,
        "longitude": -102
    },
    "MY":{
        "latitude": 2.5,
        "longitude": 112.5
    },
    "MZ":{
        "latitude": -18.25,
        "longitude": 35
    },
    "NA":{
        "latitude": -22,
        "longitude": 17
    },
    "NC":{
        "latitude": -21.5,
        "longitude": 165.5
    },
    "NE":{
        "latitude": 16,
        "longitude": 8
    },
    "NF":{
        "latitude": -29.0333,
        "longitude": 167.95
    },
    "NG":{
        "latitude": 10,
        "longitude": 8
    },
    "NI":{
        "latitude": 13,
        "longitude": -85
    },
    "NL":{
        "latitude": 52.5,
        "longitude": 5.75
    },
    "NO":{
        "latitude": 62,
        "longitude": 10
    },
    "NP":{
        "latitude": 28,
        "longitude": 84
    },
    "NR":{
        "latitude": -0.5333,
        "longitude": 166.9167
    },
    "NU":{
        "latitude": -19.0333,
        "longitude": -169.8667
    },
    "NZ":{
        "latitude": -41,
        "longitude": 174
    },
    "OM":{
        "latitude": 21,
        "longitude": 57
    },
    "PA":{
        "latitude": 9,
        "longitude": -80
    },
    "PE":{
        "latitude": -10,
        "longitude": -76
    },
    "PF":{
        "latitude": -15,
        "longitude": -140
    },
    "PG":{
        "latitude": -6,
        "longitude": 147
    },
    "PH":{
        "latitude": 13,
        "longitude": 122
    },
    "PK":{
        "latitude": 30,
        "longitude": 70
    },
    "PL":{
        "latitude": 52,
        "longitude": 20
    },
    "PM":{
        "latitude": 46.8333,
        "longitude": -56.3333
    },
    "PR":{
        "latitude": 18.25,
        "longitude": -66.5
    },
    "PS":{
        "latitude": 32,
        "longitude": 35.25
    },
    "PT":{
        "latitude": 39.5,
        "longitude": -8
    },
    "PW":{
        "latitude": 7.5,
        "longitude": 134.5
    },
    "PY":{
        "latitude": -23,
        "longitude": -58
    },
    "QA":{
        "latitude": 25.5,
        "longitude": 51.25
    },
    "RE":{
        "latitude": -21.1,
        "longitude": 55.6
    },
    "RO":{
        "latitude": 46,
        "longitude": 25
    },
    "RS":{
        "latitude": 44,
        "longitude": 21
    },
    "RU":{
        "latitude": 60,
        "longitude": 100
    },
    "RW":{
        "latitude": -2,
        "longitude": 30
    },
    "SA":{
        "latitude": 25,
        "longitude": 45
    },
    "SB":{
        "latitude": -8,
        "longitude": 159
    },
    "SC":{
        "latitude": -4.5833,
        "longitude": 55.6667
    },
    "SD":{
        "latitude": 15,
        "longitude": 30
    },
    "SE":{
        "latitude": 62,
        "longitude": 15
    },
    "SG":{
        "latitude": 1.3667,
        "longitude": 103.8
    },
    "SH":{
        "latitude": -15.9333,
        "longitude": -5.7
    },
    "SI":{
        "latitude": 46,
        "longitude": 15
    },
    "SJ":{
        "latitude": 78,
        "longitude": 20
    },
    "SK":{
        "latitude": 48.6667,
        "longitude": 19.5
    },
    "SL":{
        "latitude": 8.5,
        "longitude": -11.5
    },
    "SM":{
        "latitude": 43.7667,
        "longitude": 12.4167
    },
    "SN":{
        "latitude": 14,
        "longitude": -14
    },
    "SO":{
        "latitude": 10,
        "longitude": 49
    },
    "SR":{
        "latitude": 4,
        "longitude": -56
    },
    "ST":{
        "latitude": 1,
        "longitude": 7
    },
    "SV":{
        "latitude": 13.8333,
        "longitude": -88.9167
    },
    "SY":{
        "latitude": 35,
        "longitude": 38
    },
    "SZ":{
        "latitude": -26.5,
        "longitude": 31.5
    },
    "TC":{
        "latitude": 21.75,
        "longitude": -71.5833
    },
    "TD":{
        "latitude": 15,
        "longitude": 19
    },
    "TF":{
        "latitude": -43,
        "longitude": 67
    },
    "TG":{
        "latitude": 8,
        "longitude": 1.1667
    },
    "TH":{
        "latitude": 15,
        "longitude": 100
    },
    "TJ":{
        "latitude": 39,
        "longitude": 71
    },
    "TK":{
        "latitude": -9,
        "longitude": -172
    },
    "TM":{
        "latitude": 40,
        "longitude": 60
    },
    "TN":{
        "latitude": 34,
        "longitude": 9
    },
    "TO":{
        "latitude": -20,
        "longitude": -175
    },
    "TR":{
        "latitude": 39,
        "longitude": 35
    },
    "TT":{
        "latitude": 11,
        "longitude": -61
    },
    "TV":{
        "latitude": -8,
        "longitude": 178
    },
    "TW":{
        "latitude": 23.5,
        "longitude": 121
    },
    "TZ":{
        "latitude": -6,
        "longitude": 35
    },
    "UA":{
        "latitude": 49,
        "longitude": 32
    },
    "UG":{
        "latitude": 1,
        "longitude": 32
    },
    "UM":{
        "latitude": 19.2833,
        "longitude": 166.6
    },
    "US":{
        "latitude": 38,
        "longitude": -97
    },
    "UY":{
        "latitude": -33,
        "longitude": -56
    },
    "UZ":{
        "latitude": 41,
        "longitude": 64
    },
    "VA":{
        "latitude": 41.9,
        "longitude": 12.45
    },
    "VC":{
        "latitude": 13.25,
        "longitude": -61.2
    },
    "VE":{
        "latitude": 8,
        "longitude": -66
    },
    "VG":{
        "latitude": 18.5,
        "longitude": -64.5
    },
    "VI":{
        "latitude": 18.3333,
        "longitude": -64.8333
    },
    "VN":{
        "latitude": 16,
        "longitude": 106
    },
    "VU":{
        "latitude": -16,
        "longitude": 167
    },
    "WF":{
        "latitude": -13.3,
        "longitude": -176.2
    },
    "WS":{
        "latitude": -13.5833,
        "longitude": -172.3333
    },
    "YE":{
        "latitude": 15,
        "longitude": 48
    },
    "YT":{
        "latitude": -12.8333,
        "longitude": 45.1667
    },
    "ZA":{
        "latitude": -29,
        "longitude": 24
    },
    "ZM":{
        "latitude": -15,
        "longitude": 30
    },
    "ZW":{
        "latitude": -20,
        "longitude": 30
    }
  },
  "mapData": [
    {
      "code": "AF",
      "name": "Afghanistan",
      "value": 0,
      "color": "#eea638"
    },
    {
        "code": "AL",
        "name": "Albania",
        "value": 0,
        "color": "#d8854f"
    },
    {
        "code": "DZ",
        "name": "Algeria",
        "value": 0,
        "color": "#de4c4f"
    },
    {
        "code": "AO",
        "name": "Angola",
        "value": 0,
        "color": "#de4c4f"
    },
    {
        "code": "AR",
        "name": "Argentina",
        "value": 0,
        "color": "#86a965"
    },
    {
        "code": "AM",
        "name": "Armenia",
        "value": 0,
        "color": "#d8854f"
    },
    {
        "code": "AU",
        "name": "Australia",
        "value": 0,
        "color": "#8aabb0"
    },
    {
        "code": "AT",
        "name": "Austria",
        "value": 0,
        "color": "#d8854f"
    },
    {
        "code": "AZ",
        "name": "Azerbaijan",
        "value": 0,
        "color": "#d8854f"
    },
    {
        "code": "BH",
        "name": "Bahrain",
        "value": 0,
        "color": "#eea638"
    },
    {
        "code": "BD",
        "name": "Bangladesh",
        "value": 0,
        "color": "#eea638"
    },
    {
        "code": "BY",
        "name": "Belarus",
        "value": 0,
        "color": "#d8854f"
    },
    {
        "code": "BE",
        "name": "Belgium",
        "value": 0,
        "color": "#d8854f"
    },
    {
        "code": "BJ",
        "name": "Benin",
        "value": 0,
        "color": "#de4c4f"
    },
    {
        "code": "BT",
        "name": "Bhutan",
        "value": 0,
        "color": "#eea638"
    },
    {
        "code": "BO",
        "name": "Bolivia",
        "value": 0,
        "color": "#86a965"
    },
    {
        "code": "BA",
        "name": "Bosnia and Herzegovina",
        "value": 0,
        "color": "#d8854f"
    },
    {
        "code": "BW",
        "name": "Botswana",
        "value": 0,
        "color": "#de4c4f"
    },
    {
        "code": "BR",
        "name": "Brazil",
        "value": 0,
        "color": "#86a965"
    },
    {
        "code": "BN",
        "name": "Brunei",
        "value": 0,
        "color": "#eea638"
    },
    {
        "code": "BG",
        "name": "Bulgaria",
        "value": 0,
        "color": "#d8854f"
    },
    {
        "code": "BF",
        "name": "Burkina Faso",
        "value": 0,
        "color": "#de4c4f"
    },
    {
        "code": "BI",
        "name": "Burundi",
        "value": 0,
        "color": "#de4c4f"
    },
    {
        "code": "KH",
        "name": "Cambodia",
        "value": 0,
        "color": "#eea638"
    },
    {
        "code": "CM",
        "name": "Cameroon",
        "value": 0,
        "color": "#de4c4f"
    },
    {
        "code": "CA",
        "name": "Canada",
        "value": 0,
        "color": "#a7a737"
    },
    {
        "code": "CV",
        "name": "Cape Verde",
        "value": 0,
        "color": "#de4c4f"
    },
    {
        "code": "CF",
        "name": "Central African Rep.",
        "value": 0,
        "color": "#de4c4f"
    },
    {
        "code": "TD",
        "name": "Chad",
        "value": 0,
        "color": "#de4c4f"
    },
    {
        "code": "CL",
        "name": "Chile",
        "value": 0,
        "color": "#86a965"
    },
    {
        "code": "CN",
        "name": "China",
        "value": 0,
        "color": "#eea638"
    },
    {
        "code": "CO",
        "name": "Colombia",
        "value": 0,
        "color": "#86a965"
    },
    {
        "code": "KM",
        "name": "Comoros",
        "value": 0,
        "color": "#de4c4f"
    },
    {
        "code": "CD",
        "name": "Congo, Dem. Rep.",
        "value": 0,
        "color": "#de4c4f"
    },
    {
        "code": "CG",
        "name": "Congo, Rep.",
        "value": 0,
        "color": "#de4c4f"
    },
    {
        "code": "CR",
        "name": "Costa Rica",
        "value": 0,
        "color": "#a7a737"
    },
    {
        "code": "CI",
        "name": "Cote d'Ivoire",
        "value": 0,
        "color": "#de4c4f"
    },
    {
        "code": "HR",
        "name": "Croatia",
        "value": 0,
        "color": "#d8854f"
    },
    {
        "code": "CU",
        "name": "Cuba",
        "value": 0,
        "color": "#a7a737"
    },
    {
        "code": "CY",
        "name": "Cyprus",
        "value": 0,
        "color": "#d8854f"
    },
    {
        "code": "CZ",
        "name": "Czech Rep.",
        "value": 0,
        "color": "#d8854f"
    },
    {
        "code": "DK",
        "name": "Denmark",
        "value": 0,
        "color": "#d8854f"
    },
    {
        "code": "DJ",
        "name": "Djibouti",
        "value": 0,
        "color": "#de4c4f"
    },
    {
        "code": "DO",
        "name": "Dominican Rep.",
        "value": 0,
        "color": "#a7a737"
    },
    {
        "code": "EC",
        "name": "Ecuador",
        "value": 0,
        "color": "#86a965"
    },
    {
        "code": "EG",
        "name": "Egypt",
        "value": 0,
        "color": "#de4c4f"
    },
    {
        "code": "SV",
        "name": "El Salvador",
        "value": 0,
        "color": "#a7a737"
    },
    {
        "code": "GQ",
        "name": "Equatorial Guinea",
        "value": 0,
        "color": "#de4c4f"
    },
    {
        "code": "ER",
        "name": "Eritrea",
        "value": 0,
        "color": "#de4c4f"
    },
    {
        "code": "EE",
        "name": "Estonia",
        "value": 0,
        "color": "#d8854f"
    },
    {
        "code": "ET",
        "name": "Ethiopia",
        "value": 0,
        "color": "#de4c4f"
    },
    {
        "code": "FJ",
        "name": "Fiji",
        "value": 0,
        "color": "#8aabb0"
    },
    {
        "code": "FI",
        "name": "Finland",
        "value": 0,
        "color": "#d8854f"
    },
    {
        "code": "FR",
        "name": "France",
        "value": 0,
        "color": "#d8854f"
    },
    {
        "code": "GA",
        "name": "Gabon",
        "value": 0,
        "color": "#de4c4f"
    },
    {
        "code": "GM",
        "name": "Gambia",
        "value": 0,
        "color": "#de4c4f"
    },
    {
        "code": "GE",
        "name": "Georgia",
        "value": 0,
        "color": "#d8854f"
    },
    {
        "code": "DE",
        "name": "Germany",
        "value": 0,
        "color": "#d8854f"
    },
    {
        "code": "GH",
        "name": "Ghana",
        "value": 0,
        "color": "#de4c4f"
    },
    {
        "code": "GR",
        "name": "Greece",
        "value": 0,
        "color": "#d8854f"
    },
    {
        "code": "GT",
        "name": "Guatemala",
        "value": 0,
        "color": "#a7a737"
    },
    {
        "code": "GN",
        "name": "Guinea",
        "value": 0,
        "color": "#de4c4f"
    },
    {
        "code": "GW",
        "name": "Guinea-Bissau",
        "value": 0,
        "color": "#de4c4f"
    },
    {
        "code": "GY",
        "name": "Guyana",
        "value": 0,
        "color": "#86a965"
    },
    {
        "code": "HT",
        "name": "Haiti",
        "value": 0,
        "color": "#a7a737"
    },
    {
        "code": "HN",
        "name": "Honduras",
        "value": 0,
        "color": "#a7a737"
    },
    {
        "code": "HK",
        "name": "Hong Kong, China",
        "value": 0,
        "color": "#eea638"
    },
    {
        "code": "HU",
        "name": "Hungary",
        "value": 0,
        "color": "#d8854f"
    },
    {
        "code": "IS",
        "name": "Iceland",
        "value": 0,
        "color": "#d8854f"
    },
    {
        "code": "IN",
        "name": "India",
        "value": 0,
        "color": "#eea638"
    },
    {
        "code": "ID",
        "name": "Indonesia",
        "value": 0,
        "color": "#eea638"
    },
    {
        "code": "IR",
        "name": "Iran",
        "value": 0,
        "color": "#eea638"
    },
    {
        "code": "IQ",
        "name": "Iraq",
        "value": 0,
        "color": "#eea638"
    },
    {
        "code": "IE",
        "name": "Ireland",
        "value": 0,
        "color": "#d8854f"
    },
    {
        "code": "IL",
        "name": "Israel",
        "value": 0,
        "color": "#eea638"
    },
    {
        "code": "IT",
        "name": "Italy",
        "value": 0,
        "color": "#d8854f"
    },
    {
        "code": "JM",
        "name": "Jamaica",
        "value": 0,
        "color": "#a7a737"
    },
    {
        "code": "JP",
        "name": "Japan",
        "value": 0,
        "color": "#eea638"
    },
    {
        "code": "JO",
        "name": "Jordan",
        "value": 0,
        "color": "#eea638"
    },
    {
        "code": "KZ",
        "name": "Kazakhstan",
        "value": 0,
        "color": "#eea638"
    },
    {
        "code": "KE",
        "name": "Kenya",
        "value": 0,
        "color": "#de4c4f"
    },
    {
        "code": "KR",
        "name": "Korea, Dem. Rep.",
        "value": 0,
        "color": "#eea638"
    },
    {
        "code": "KP",
        "name": "Korea, Rep.",
        "value": 0,
        "color": "#eea638"
    },
    {
        "code": "KW",
        "name": "Kuwait",
        "value": 0,
        "color": "#eea638"
    },
    {
        "code": "KG",
        "name": "Kyrgyzstan",
        "value": 0,
        "color": "#eea638"
    },
    {
        "code": "LA",
        "name": "Laos",
        "value": 0,
        "color": "#eea638"
    },
    {
        "code": "LV",
        "name": "Latvia",
        "value": 0,
        "color": "#d8854f"
    },
    {
        "code": "LB",
        "name": "Lebanon",
        "value": 0,
        "color": "#eea638"
    },
    {
        "code": "LS",
        "name": "Lesotho",
        "value": 0,
        "color": "#de4c4f"
    },
    {
        "code": "LR",
        "name": "Liberia",
        "value": 0,
        "color": "#de4c4f"
    },
    {
        "code": "LY",
        "name": "Libya",
        "value": 0,
        "color": "#de4c4f"
    },
    {
        "code": "LT",
        "name": "Lithuania",
        "value": 0,
        "color": "#d8854f"
    },
    {
        "code": "LU",
        "name": "Luxembourg",
        "value": 0,
        "color": "#d8854f"
    },
    {
        "code": "MK",
        "name": "Macedonia, FYR",
        "value": 0,
        "color": "#d8854f"
    },
    {
        "code": "MG",
        "name": "Madagascar",
        "value": 0,
        "color": "#de4c4f"
    },
    {
        "code": "MW",
        "name": "Malawi",
        "value": 0,
        "color": "#de4c4f"
    },
    {
        "code": "MY",
        "name": "Malaysia",
        "value": 0,
        "color": "#eea638"
    },
    {
        "code": "ML",
        "name": "Mali",
        "value": 0,
        "color": "#de4c4f"
    },
    {
        "code": "MR",
        "name": "Mauritania",
        "value": 0,
        "color": "#de4c4f"
    },
    {
        "code": "MU",
        "name": "Mauritius",
        "value": 0,
        "color": "#de4c4f"
    },
    {
        "code": "MX",
        "name": "Mexico",
        "value": 0,
        "color": "#a7a737"
    },
    {
        "code": "MD",
        "name": "Moldova",
        "value": 0,
        "color": "#d8854f"
    },
    {
        "code": "MN",
        "name": "Mongolia",
        "value": 0,
        "color": "#eea638"
    },
    {
        "code": "ME",
        "name": "Montenegro",
        "value": 0,
        "color": "#d8854f"
    },
    {
        "code": "MA",
        "name": "Morocco",
        "value": 0,
        "color": "#de4c4f"
    },
    {
        "code": "MZ",
        "name": "Mozambique",
        "value": 0,
        "color": "#de4c4f"
    },
    {
        "code": "MM",
        "name": "Myanmar",
        "value": 0,
        "color": "#eea638"
    },
    {
        "code": "NA",
        "name": "Namibia",
        "value": 0,
        "color": "#de4c4f"
    },
    {
        "code": "NP",
        "name": "Nepal",
        "value": 0,
        "color": "#eea638"
    },
    {
        "code": "NL",
        "name": "Netherlands",
        "value": 0,
        "color": "#d8854f"
    },
    {
        "code": "NZ",
        "name": "New Zealand",
        "value": 0,
        "color": "#8aabb0"
    },
    {
        "code": "NI",
        "name": "Nicaragua",
        "value": 0,
        "color": "#a7a737"
    },
    {
        "code": "NE",
        "name": "Niger",
        "value": 0,
        "color": "#de4c4f"
    },
    {
        "code": "NG",
        "name": "Nigeria",
        "value": 0,
        "color": "#de4c4f"
    },
    {
        "code": "NO",
        "name": "Norway",
        "value": 0,
        "color": "#d8854f"
    },
    {
        "code": "OM",
        "name": "Oman",
        "value": 0,
        "color": "#eea638"
    },
    {
        "code": "PK",
        "name": "Pakistan",
        "value": 0,
        "color": "#eea638"
    },
    {
        "code": "PA",
        "name": "Panama",
        "value": 0,
        "color": "#a7a737"
    },
    {
        "code": "PG",
        "name": "Papua New Guinea",
        "value": 0,
        "color": "#8aabb0"
    },
    {
        "code": "PY",
        "name": "Paraguay",
        "value": 0,
        "color": "#86a965"
    },
    {
        "code": "PE",
        "name": "Peru",
        "value": 0,
        "color": "#86a965"
    },
    {
        "code": "PH",
        "name": "Philippines",
        "value": 0,
        "color": "#eea638"
    },
    {
        "code": "PL",
        "name": "Poland",
        "value": 0,
        "color": "#d8854f"
    },
    {
        "code": "PT",
        "name": "Portugal",
        "value": 0,
        "color": "#d8854f"
    },
    {
        "code": "PR",
        "name": "Puerto Rico",
        "value": 0,
        "color": "#a7a737"
    },
    {
        "code": "QA",
        "name": "Qatar",
        "value": 0,
        "color": "#eea638"
    },
    {
        "code": "RO",
        "name": "Romania",
        "value": 0,
        "color": "#d8854f"
    },
    {
        "code": "RU",
        "name": "Russia",
        "value": 0,
        "color": "#d8854f"
    },
    {
        "code": "RW",
        "name": "Rwanda",
        "value": 0,
        "color": "#de4c4f"
    },
    {
        "code": "SA",
        "name": "Saudi Arabia",
        "value": 0,
        "color": "#eea638"
    },
    {
        "code": "SN",
        "name": "Senegal",
        "value": 0,
        "color": "#de4c4f"
    },
    {
        "code": "RS",
        "name": "Serbia",
        "value": 0,
        "color": "#d8854f"
    },
    {
        "code": "SL",
        "name": "Sierra Leone",
        "value": 0,
        "color": "#de4c4f"
    },
    {
        "code": "SG",
        "name": "Singapore",
        "value": 0,
        "color": "#eea638"
    },
    {
        "code": "SK",
        "name": "Slovak Republic",
        "value": 0,
        "color": "#d8854f"
    },
    {
        "code": "SI",
        "name": "Slovenia",
        "value": 0,
        "color": "#d8854f"
    },
    {
        "code": "SB",
        "name": "Solomon Islands",
        "value": 0,
        "color": "#8aabb0"
    },
    {
        "code": "SO",
        "name": "Somalia",
        "value": 0,
        "color": "#de4c4f"
    },
    {
        "code": "ZA",
        "name": "South Africa",
        "value": 0,
        "color": "#de4c4f"
    },
    {
        "code": "ES",
        "name": "Spain",
        "value": 0,
        "color": "#d8854f"
    },
    {
        "code": "LK",
        "name": "Sri Lanka",
        "value": 0,
        "color": "#eea638"
    },
    {
        "code": "SD",
        "name": "Sudan",
        "value": 0,
        "color": "#de4c4f"
    },
    {
        "code": "SR",
        "name": "Suriname",
        "value": 0,
        "color": "#86a965"
    },
    {
        "code": "SZ",
        "name": "Swaziland",
        "value": 0,
        "color": "#de4c4f"
    },
    {
        "code": "SE",
        "name": "Sweden",
        "value": 0,
        "color": "#d8854f"
    },
    {
        "code": "CH",
        "name": "Switzerland",
        "value": 0,
        "color": "#d8854f"
    },
    {
        "code": "SY",
        "name": "Syria",
        "value": 0,
        "color": "#eea638"
    },
    {
        "code": "TW",
        "name": "Taiwan",
        "value": 0,
        "color": "#eea638"
    },
    {
        "code": "TJ",
        "name": "Tajikistan",
        "value": 0,
        "color": "#eea638"
    },
    {
        "code": "TZ",
        "name": "Tanzania",
        "value": 0,
        "color": "#de4c4f"
    },
    {
        "code": "TH",
        "name": "Thailand",
        "value": 0,
        "color": "#eea638"
    },
    {
        "code": "TG",
        "name": "Togo",
        "value": 0,
        "color": "#de4c4f"
    },
    {
        "code": "TT",
        "name": "Trinidad and Tobago",
        "value": 0,
        "color": "#a7a737"
    },
    {
        "code": "TN",
        "name": "Tunisia",
        "value": 0,
        "color": "#de4c4f"
    },
    {
        "code": "TR",
        "name": "Turkey",
        "value": 0,
        "color": "#d8854f"
    },
    {
        "code": "TM",
        "name": "Turkmenistan",
        "value": 0,
        "color": "#eea638"
    },
    {
        "code": "UG",
        "name": "Uganda",
        "value": 0,
        "color": "#de4c4f"
    },
    {
        "code": "UA",
        "name": "Ukraine",
        "value": 0,
        "color": "#d8854f"
    },
    {
        "code": "AE",
        "name": "United Arab Emirates",
        "value": 0,
        "color": "#eea638"
    },
    {
        "code": "GB",
        "name": "United Kingdom",
        "value": 0,
        "color": "#d8854f"
    },
    {
        "code": "US",
        "name": "United States",
        "value": 0,
        "color": "#a7a737"
    },
    {
        "code": "UY",
        "name": "Uruguay",
        "value": 0,
        "color": "#86a965"
    },
    {
        "code": "UZ",
        "name": "Uzbekistan",
        "value": 0,
        "color": "#eea638"
    },
    {
        "code": "VE",
        "name": "Venezuela",
        "value": 0,
        "color": "#86a965"
    },
    {
        "code": "PS",
        "name": "West Bank and Gaza",
        "value": 0,
        "color": "#eea638"
    },
    {
        "code": "VN",
        "name": "Vietnam",
        "value": 0,
        "color": "#eea638"
    },
    {
        "code": "YE",
        "name": "Yemen, Rep.",
        "value": 0,
        "color": "#eea638"
    },
    {
        "code": "ZM",
        "name": "Zambia",
        "value": 0,
        "color": "#de4c4f"
    },
    {
        "code": "ZW",
        "name": "Zimbabwe",
        "value": 0,
        "color": "#de4c4f"
    }
  ],
  "minBulletSize": 3,
  "maxBulletSize": 70,
  "images": [
    {
        "zoomLevel": 6, "type": "circle",           "width": 0,           "height": 0,
        "alpha": 0.2,
        "rollOverColor": "#fff",
        "rollOverScale": 1,
        "selectedScale": 2,
        "Scale": 0.5,
        "title": "Washington",
        "latitude": 38.8921,
        "longitude": -77.0241
    },
    {
        
        "zoomLevel": 6, "type": "circle",           "width": 0,           "height": 0,
        "alpha": 0.2,
        "rollOverColor": "#fff",
        "rollOverScale": 1,
        "selectedScale": 2,
        "Scale": 0.5,
        "title": "Buenos Aires",
        "latitude": -34.6118,
        "longitude": -58.4173
    },
    {
        
        "zoomLevel": 6, "type": "circle",           "width": 0,           "height": 0,
        "alpha": 0.2,
        "rollOverColor": "#fff",
        "rollOverScale": 1,
        "selectedScale": 2,
        "Scale": 0.5,
        "title": "Tokyo",
        "latitude": 35.6785,
        "longitude": 139.6823
    },
    {
        
        "zoomLevel": 6, "type": "circle",           "width": 0,           "height": 0,
        "alpha": 0.2,
        "rollOverColor": "#fff",
        "rollOverScale": 1,
        "selectedScale": 2,
        "Scale": 0.5,
        "title": "Vienna",
        "latitude": 48.2092,
        "longitude": 16.3728
    },
    {
        
        "zoomLevel": 6, "type": "circle",           "width": 0,           "height": 0,
        "alpha": 0.2,
        "rollOverColor": "#fff",
        "rollOverScale": 1,
        "selectedScale": 2,
        "Scale": 0.5,
        "title": "Brasilia",
        "latitude": -15.7801,
        "longitude": -47.9292
    },
    {
        
        "zoomLevel": 6, "type": "circle",           "width": 0,           "height": 0,
        "alpha": 0.2,
        "rollOverColor": "#fff",
        "rollOverScale": 1,
        "selectedScale": 2,
        "Scale": 0.5,
        "title": "Amsterdam",
        "latitude": 52.3738,
        "longitude": 4.8910
    },
    {
        
        "zoomLevel": 6, "type": "circle",           "width": 0,           "height": 0,
        "alpha": 0.2,
        "rollOverColor": "#fff",
        "rollOverScale": 1,
        "selectedScale": 2,
        "Scale": 0.5,
        "title": "London",
        "latitude": 51.5002,
        "longitude": -0.1262
    },
    {
        
        "zoomLevel": 6, "type": "circle",           "width": 0,           "height": 0,
        "alpha": 0.2,
        "rollOverColor": "#fff",
        "rollOverScale": 1,
        "selectedScale": 2,
        "Scale": 0.5,
        "title": "Brussels",
        "latitude": 50.8371,
        "longitude": 4.3676
    },
    {
        
        "zoomLevel": 6, "type": "circle",           "width": 0,           "height": 0,
        "alpha": 0.2,
        "rollOverColor": "#fff",
        "rollOverScale": 1,
        "selectedScale": 2,
        "Scale": 0.5,
        "title": "Madrid",
        "latitude": 40.4167,
        "longitude": -3.7033
    },
    {
        
        "zoomLevel": 6, "type": "circle",           "width": 0,           "height": 0,
        "alpha": 0.2,
        "rollOverColor": "#fff",
        "rollOverScale": 1,
        "selectedScale": 2,
        "Scale": 0.5,
        "title": "Helsinki",
        "latitude": 60.1699,
        "longitude": 24.9384
    },
    {
        
        "zoomLevel": 6, "type": "circle",           "width": 0,           "height": 0,
        "alpha": 0.2,
        "rollOverColor": "#fff",
        "rollOverScale": 1,
        "selectedScale": 2,
        "Scale": 0.5,
        "title": "Paris",
        "latitude": 48.8567,
        "longitude": 2.3510
    },
    {
        
        "zoomLevel": 6, "type": "circle",           "width": 0,           "height": 0,
        "alpha": 0.2,
        "rollOverColor": "#fff",
        "rollOverScale": 1,
        "selectedScale": 2,
        "Scale": 0.5,
        "title": "Berlin",
        "latitude": 52.5235,
        "longitude": 13.4115
    },
    {
        
        "zoomLevel": 6, "type": "circle",           "width": 0,           "height": 0,
        "alpha": 0.2,
        "rollOverColor": "#fff",
        "rollOverScale": 1,
        "selectedScale": 2,
        "Scale": 0.5,
        "title": "Rome",
        "latitude": 41.8955,
        "longitude": 12.4823
    },
    {
        
        "zoomLevel": 6, "type": "circle",           "width": 0,           "height": 0,
        "alpha": 0.2,
        "rollOverColor": "#fff",
        "rollOverScale": 1,
        "selectedScale": 2,
        "Scale": 0.5,
        "title": "Athens",
        "latitude": 37.9792,
        "longitude": 23.7166
    },
    {
        
        "zoomLevel": 6, "type": "circle",           "width": 0,           "height": 0,
        "alpha": 0.2,
        "rollOverColor": "#fff",
        "rollOverScale": 1,
        "selectedScale": 2,
        "Scale": 0.5,
        "title": "Budapest",
        "latitude": 47.4984,
        "longitude": 19.0408
    },
    {
        
        "zoomLevel": 6, "type": "circle",           "width": 0,           "height": 0,
        "alpha": 0.2,
        "rollOverColor": "#fff",
        "rollOverScale": 1,
        "selectedScale": 2,
        "Scale": 0.5,
        "title": "Reykjavik",
        "latitude": 64.1353,
        "longitude": -21.8952
    },
    {
        
        "zoomLevel": 6, "type": "circle",           "width": 0,           "height": 0,
        "alpha": 0.2,
        "rollOverColor": "#fff",
        "rollOverScale": 1,
        "selectedScale": 2,
        "Scale": 0.5,
        "title": "Dublin",
        "latitude": 53.3441,
        "longitude": -6.2675
    },
    {
        
        "zoomLevel": 6, "type": "circle",           "width": 0,           "height": 0,
        "alpha": 0.2,
        "rollOverColor": "#fff",
        "rollOverScale": 1,
        "selectedScale": 2,
        "Scale": 0.5,
        "title": "Riga",
        "latitude": 56.9465,
        "longitude": 24.1049
    },
    {
        
        "zoomLevel": 6, "type": "circle",           "width": 0,           "height": 0,
        "alpha": 0.2,
        "rollOverColor": "#fff",
        "rollOverScale": 1,
        "selectedScale": 2,
        "Scale": 0.5,
        "title": "Vaduz",
        "latitude": 47.1411,
        "longitude": 9.5215
    },
    {
        
        "zoomLevel": 6, "type": "circle",           "width": 0,           "height": 0,
        "alpha": 0.2,
        "rollOverColor": "#fff",
        "rollOverScale": 1,
        "selectedScale": 2,
        "Scale": 0.5,
        "title": "Vilnius",
        "latitude": 54.6896,
        "longitude": 25.2799
    },
    {
        
        "zoomLevel": 6, "type": "circle",           "width": 0,           "height": 0,
        "alpha": 0.2,
        "rollOverColor": "#fff",
        "rollOverScale": 1,
        "selectedScale": 2,
        "Scale": 0.5,
        "title": "Luxembourg",
        "latitude": 49.6100,
        "longitude": 6.1296
    },
    {
        
        "zoomLevel": 6, "type": "circle",           "width": 0,           "height": 0,
        "alpha": 0.2,
        "rollOverColor": "#fff",
        "rollOverScale": 1,
        "selectedScale": 2,
        "Scale": 0.5,
        "title": "Skopje",
        "latitude": 42.0024,
        "longitude": 21.4361
    },
    {
        
        "zoomLevel": 6, "type": "circle",           "width": 0,           "height": 0,
        "alpha": 0.2,
        "rollOverColor": "#fff",
        "rollOverScale": 1,
        "selectedScale": 2,
        "Scale": 0.5,
        "title": "Valletta",
        "latitude": 35.9042,
        "longitude": 14.5189
    },
    {
        
        "zoomLevel": 6, "type": "circle",           "width": 0,           "height": 0,
        "alpha": 0.2,
        "rollOverColor": "#fff",
        "rollOverScale": 1,
        "selectedScale": 2,
        "Scale": 0.5,
        "title": "Chisinau",
        "latitude": 47.0167,
        "longitude": 28.8497
    },
    {
        
        "zoomLevel": 6, "type": "circle",           "width": 0,           "height": 0,
        "alpha": 0.2,
        "rollOverColor": "#fff",
        "rollOverScale": 1,
        "selectedScale": 2,
        "Scale": 0.5,
        "title": "Monaco",
        "latitude": 43.7325,
        "longitude": 7.4189
    },
    {
        
        "zoomLevel": 6, "type": "circle",           "width": 0,           "height": 0,
        "alpha": 0.2,
        "rollOverColor": "#fff",
        "rollOverScale": 1,
        "selectedScale": 2,
        "Scale": 0.5,
        "title": "Podgorica",
        "latitude": 42.4602,
        "longitude": 19.2595
    },
    {
        
        "zoomLevel": 6, "type": "circle",           "width": 0,           "height": 0,
        "alpha": 0.2,
        "rollOverColor": "#fff",
        "rollOverScale": 1,
        "selectedScale": 2,
        "Scale": 0.5,
        "title": "Oslo",
        "latitude": 59.9138,
        "longitude": 10.7387
    },
    {
        
        "zoomLevel": 6, "type": "circle",           "width": 0,           "height": 0,
        "alpha": 0.2,
        "rollOverColor": "#fff",
        "rollOverScale": 1,
        "selectedScale": 2,
        "Scale": 0.5,
        "title": "Warsaw",
        "latitude": 52.2297,
        "longitude": 21.0122
    },
    {
        
        "zoomLevel": 6, "type": "circle",           "width": 0,           "height": 0,
        "alpha": 0.2,
        "rollOverColor": "#fff",
        "rollOverScale": 1,
        "selectedScale": 2,
        "Scale": 0.5,
        "title": "Lisbon",
        "latitude": 38.7072,
        "longitude": -9.1355
    },
    {
        
        "zoomLevel": 6, "type": "circle",           "width": 0,           "height": 0,
        "alpha": 0.2,
        "rollOverColor": "#fff",
        "rollOverScale": 1,
        "selectedScale": 2,
        "Scale": 0.5,
        "title": "Bucharest",
        "latitude": 44.4479,
        "longitude": 26.0979
    },
    {
        
        "zoomLevel": 6, "type": "circle",           "width": 0,           "height": 0,
        "alpha": 0.2,
        "rollOverColor": "#fff",
        "rollOverScale": 1,
        "selectedScale": 2,
        "Scale": 0.5,
        "title": "Moscow",
        "latitude": 55.7558,
        "longitude": 37.6176
    },
    {
        
        "zoomLevel": 6, "type": "circle",           "width": 0,           "height": 0,
        "alpha": 0.2,
        "rollOverColor": "#fff",
        "rollOverScale": 1,
        "selectedScale": 2,
        "Scale": 0.5,
        "title": "San Marino",
        "latitude": 43.9424,
        "longitude": 12.4578
    },
    {
        
        "zoomLevel": 6, "type": "circle",           "width": 0,           "height": 0,
        "alpha": 0.2,
        "rollOverColor": "#fff",
        "rollOverScale": 1,
        "selectedScale": 2,
        "Scale": 0.5,
        "title": "Belgrade",
        "latitude": 44.8048,
        "longitude": 20.4781
    },
    {
        
        "zoomLevel": 6, "type": "circle",           "width": 0,           "height": 0,
        "alpha": 0.2,
        "rollOverColor": "#fff",
        "rollOverScale": 1,
        "selectedScale": 2,
        "Scale": 0.5,
        "title": "Bratislava",
        "latitude": 48.2116,
        "longitude": 17.1547
    },
    {
        
        "zoomLevel": 6, "type": "circle",           "width": 0,           "height": 0,
        "alpha": 0.2,
        "rollOverColor": "#fff",
        "rollOverScale": 1,
        "selectedScale": 2,
        "Scale": 0.5,
        "title": "Ljubljana",
        "latitude": 46.0514,
        "longitude": 14.5060
    },
    {
        
        "zoomLevel": 6, "type": "circle",           "width": 0,           "height": 0,
        "alpha": 0.2,
        "rollOverColor": "#fff",
        "rollOverScale": 1,
        "selectedScale": 2,
        "Scale": 0.5,
        "title": "Stockholm",
        "latitude": 59.3328,
        "longitude": 18.0645
    },
    {
        
        "zoomLevel": 6, "type": "circle",           "width": 0,           "height": 0,
        "alpha": 0.2,
        "rollOverColor": "#fff",
        "rollOverScale": 1,
        "selectedScale": 2,
        "Scale": 0.5,
        "title": "Bern",
        "latitude": 46.9480,
        "longitude": 7.4481
    },
    {
        
        "zoomLevel": 6, "type": "circle",           "width": 0,           "height": 0,
        "alpha": 0.2,
        "rollOverColor": "#fff",
        "rollOverScale": 1,
        "selectedScale": 2,
        "Scale": 0.5,
        "title": "Kiev",
        "latitude": 50.4422,
        "longitude": 30.5367
    },
    {
        
        "zoomLevel": 6, "type": "circle",           "width": 0,           "height": 0,
        "alpha": 0.2,
        "rollOverColor": "#fff",
        "rollOverScale": 1,
        "selectedScale": 2,
        "Scale": 0.5,
        "title": "Gibraltar",
        "latitude": 36.1377,
        "longitude": -5.3453
    },
    {
        
        "zoomLevel": 6, "type": "circle",           "width": 0,           "height": 0,
        "alpha": 0.2,
        "rollOverColor": "#fff",
        "rollOverScale": 1,
        "selectedScale": 2,
        "Scale": 0.5,
        "title": "Saint Peter Port",
        "latitude": 49.4660,
        "longitude": -2.5522
    },
    {
        
        "zoomLevel": 6, "type": "circle",           "width": 0,           "height": 0,
        "alpha": 0.2,
        "rollOverColor": "#fff",
        "rollOverScale": 1,
        "selectedScale": 2,
        "Scale": 0.5,
        "title": "Douglas",
        "latitude": 54.1670,
        "longitude": -4.4821
    },
    {
        
        "zoomLevel": 6, "type": "circle",           "width": 0,           "height": 0,
        "alpha": 0.2,
        "rollOverColor": "#fff",
        "rollOverScale": 1,
        "selectedScale": 2,
        "Scale": 0.5,
        "title": "Saint Helier",
        "latitude": 49.1919,
        "longitude": -2.1071
    },
    {
        
        "zoomLevel": 6, "type": "circle",           "width": 0,           "height": 0,
        "alpha": 0.2,
        "rollOverColor": "#fff",
        "rollOverScale": 1,
        "selectedScale": 2,
        "Scale": 0.5,
        "title": "Longyearbyen",
        "latitude": 78.2186,
        "longitude": 15.6488
    },
    {
        
        "zoomLevel": 6, "type": "circle",           "width": 0,           "height": 0,
        "alpha": 0.2,
        "rollOverColor": "#fff",
        "rollOverScale": 1,
        "selectedScale": 2,
        "Scale": 0.5,
        "title": "Kabul",
        "latitude": 34.5155,
        "longitude": 69.1952
    },
    {
        
        "zoomLevel": 6, "type": "circle",           "width": 0,           "height": 0,
        "alpha": 0.2,
        "rollOverColor": "#fff",
        "rollOverScale": 1,
        "selectedScale": 2,
        "Scale": 0.5,
        "title": "Yerevan",
        "latitude": 40.1596,
        "longitude": 44.5090
    },
    {
        
        "zoomLevel": 6, "type": "circle",           "width": 0,           "height": 0,
        "alpha": 0.2,
        "rollOverColor": "#fff",
        "rollOverScale": 1,
        "selectedScale": 2,
        "Scale": 0.5,
        "title": "Baku",
        "latitude": 40.3834,
        "longitude": 49.8932
    },
    {
        
        "zoomLevel": 6, "type": "circle",           "width": 0,           "height": 0,
        "alpha": 0.2,
        "rollOverColor": "#fff",
        "rollOverScale": 1,
        "selectedScale": 2,
        "Scale": 0.5,
        "title": "Manama",
        "latitude": 26.1921,
        "longitude": 50.5354
    },
    {
        
        "zoomLevel": 6, "type": "circle",           "width": 0,           "height": 0,
        "alpha": 0.2,
        "rollOverColor": "#fff",
        "rollOverScale": 1,
        "selectedScale": 2,
        "Scale": 0.5,
        "title": "Zagreb",
        "latitude": 45.8150,
        "longitude": 15.9785
    },
    {
        
        "zoomLevel": 6, "type": "circle",           "width": 0,           "height": 0,
        "alpha": 0.2,
        "rollOverColor": "#fff",
        "rollOverScale": 1,
        "selectedScale": 2,
        "Scale": 0.5,
        "title": "Sarajevo",
        "latitude": 43.8608,
        "longitude": 18.4214
    },
    {
        
        "zoomLevel": 6, "type": "circle",           "width": 0,           "height": 0,
        "alpha": 0.2,
        "rollOverColor": "#fff",
        "rollOverScale": 1,
        "selectedScale": 2,
        "Scale": 0.5,
        "title": "Sofia",
        "latitude": 42.7105,
        "longitude": 23.3238
    },
    {
        
        "zoomLevel": 6, "type": "circle",           "width": 0,           "height": 0,
        "alpha": 0.2,
        "rollOverColor": "#fff",
        "rollOverScale": 1,
        "selectedScale": 2,
        "Scale": 0.5,
        "title": "Prague",
        "latitude": 50.0878,
        "longitude": 14.4205
    },
    {
        
        "zoomLevel": 6, "type": "circle",           "width": 0,           "height": 0,
        "alpha": 0.2,
        "rollOverColor": "#fff",
        "rollOverScale": 1,
        "selectedScale": 2,
        "Scale": 0.5,
        "title": "Copenhagen",
        "latitude": 55.6763,
        "longitude": 12.5681
    },
    {
        
        "zoomLevel": 6, "type": "circle",           "width": 0,           "height": 0,
        "alpha": 0.2,
        "rollOverColor": "#fff",
        "rollOverScale": 1,
        "selectedScale": 2,
        "Scale": 0.5,
        "title": "Pristina",
        "latitude": 42.666667,
        "longitude": 21.166667
    },
    {
        
        "zoomLevel": 6, "type": "circle",           "width": 0,           "height": 0,
        "alpha": 0.2,
        "rollOverColor": "#fff",
        "rollOverScale": 1,
        "selectedScale": 2,
        "Scale": 0.5,
        "title": "Dhaka",
        "latitude": 23.7106,
        "longitude": 90.3978
    },
    {
        
        "zoomLevel": 6, "type": "circle",           "width": 0,           "height": 0,
        "alpha": 0.2,
        "rollOverColor": "#fff",
        "rollOverScale": 1,
        "selectedScale": 2,
        "Scale": 0.5,
        "title": "Thimphu",
        "latitude": 27.4405,
        "longitude": 89.6730
    },
    {
        
        "zoomLevel": 6, "type": "circle",           "width": 0,           "height": 0,
        "alpha": 0.2,
        "rollOverColor": "#fff",
        "rollOverScale": 1,
        "selectedScale": 2,
        "Scale": 0.5,
        "title": "Bandar Seri Begawan",
        "latitude": 4.9431,
        "longitude": 114.9425
    },
    {
        
        "zoomLevel": 6, "type": "circle",           "width": 0,           "height": 0,
        "alpha": 0.2,
        "rollOverColor": "#fff",
        "rollOverScale": 1,
        "selectedScale": 2,
        "Scale": 0.5,
        "title": "Phnom Penh",
        "latitude": 11.5434,
        "longitude": 104.8984
    },
    {
        
        "zoomLevel": 6, "type": "circle",           "width": 0,           "height": 0,
        "alpha": 0.2,
        "rollOverColor": "#fff",
        "rollOverScale": 1,
        "selectedScale": 2,
        "Scale": 0.5,
        "title": "Peking",
        "latitude": 39.9056,
        "longitude": 116.3958
    },
    {
        
        "zoomLevel": 6, "type": "circle",           "width": 0,           "height": 0,
        "alpha": 0.2,
        "rollOverColor": "#fff",
        "rollOverScale": 1,
        "selectedScale": 2,
        "Scale": 0.5,
        "title": "Nicosia",
        "latitude": 35.1676,
        "longitude": 33.3736
    },
    {
        
        "zoomLevel": 6, "type": "circle",           "width": 0,           "height": 0,
        "alpha": 0.2,
        "rollOverColor": "#fff",
        "rollOverScale": 1,
        "selectedScale": 2,
        "Scale": 0.5,
        "title": "T'bilisi",
        "latitude": 41.7010,
        "longitude": 44.7930
    },
    {
        
        "zoomLevel": 6, "type": "circle",           "width": 0,           "height": 0,
        "alpha": 0.2,
        "rollOverColor": "#fff",
        "rollOverScale": 1,
        "selectedScale": 2,
        "Scale": 0.5,
        "title": "New Delhi",
        "latitude": 28.6353,
        "longitude": 77.2250
    },
    {
        
        "zoomLevel": 6, "type": "circle",           "width": 0,           "height": 0,
        "alpha": 0.2,
        "rollOverColor": "#fff",
        "rollOverScale": 1,
        "selectedScale": 2,
        "Scale": 0.5,
        "title": "Jakarta",
        "latitude": -6.1862,
        "longitude": 106.8063
    },
    {
        
        "zoomLevel": 6, "type": "circle",           "width": 0,           "height": 0,
        "alpha": 0.2,
        "rollOverColor": "#fff",
        "rollOverScale": 1,
        "selectedScale": 2,
        "Scale": 0.5,
        "title": "Teheran",
        "latitude": 35.7061,
        "longitude": 51.4358
    },
    {
        
        "zoomLevel": 6, "type": "circle",           "width": 0,           "height": 0,
        "alpha": 0.2,
        "rollOverColor": "#fff",
        "rollOverScale": 1,
        "selectedScale": 2,
        "Scale": 0.5,
        "title": "Baghdad",
        "latitude": 33.3157,
        "longitude": 44.3922
    },
    {
        
        "zoomLevel": 6, "type": "circle",           "width": 0,           "height": 0,
        "alpha": 0.2,
        "rollOverColor": "#fff",
        "rollOverScale": 1,
        "selectedScale": 2,
        "Scale": 0.5,
        "title": "Minsk",
        "latitude": 53.9678,
        "longitude": 27.5766
    },
    {
        
        "zoomLevel": 6, "type": "circle",           "width": 0,           "height": 0,
        "alpha": 0.2,
        "rollOverColor": "#fff",
        "rollOverScale": 1,
        "selectedScale": 2,
        "Scale": 0.5,
        "title": "Jerusalem",
        "latitude": 31.7857,
        "longitude": 35.2007
    },
    {
        
        "zoomLevel": 6, "type": "circle",           "width": 0,           "height": 0,
        "alpha": 0.2,
        "rollOverColor": "#fff",
        "rollOverScale": 1,
        "selectedScale": 2,
        "Scale": 0.5,
        "title": "Amman",
        "latitude": 31.9394,
        "longitude": 35.9349
    },
    {
        
        "zoomLevel": 6, "type": "circle",           "width": 0,           "height": 0,
        "alpha": 0.2,
        "rollOverColor": "#fff",
        "rollOverScale": 1,
        "selectedScale": 2,
        "Scale": 0.5,
        "title": "Astana",
        "latitude": 51.1796,
        "longitude": 71.4475
    },
    {
        
        "zoomLevel": 6, "type": "circle",           "width": 0,           "height": 0,
        "alpha": 0.2,
        "rollOverColor": "#fff",
        "rollOverScale": 1,
        "selectedScale": 2,
        "Scale": 0.5,
        "title": "Kuwait",
        "latitude": 29.3721,
        "longitude": 47.9824
    },
    {
        
        "zoomLevel": 6, "type": "circle",           "width": 0,           "height": 0,
        "alpha": 0.2,
        "rollOverColor": "#fff",
        "rollOverScale": 1,
        "selectedScale": 2,
        "Scale": 0.5,
        "title": "Tallinn",
        "latitude": 59.4389,
        "longitude": 24.7545
    },
    {
        
        "zoomLevel": 6, "type": "circle",           "width": 0,           "height": 0,
        "alpha": 0.2,
        "rollOverColor": "#fff",
        "rollOverScale": 1,
        "selectedScale": 2,
        "Scale": 0.5,
        "title": "Bishkek",
        "latitude": 42.8679,
        "longitude": 74.5984
    },
    {
        
        "zoomLevel": 6, "type": "circle",           "width": 0,           "height": 0,
        "alpha": 0.2,
        "rollOverColor": "#fff",
        "rollOverScale": 1,
        "selectedScale": 2,
        "Scale": 0.5,
        "title": "Vientiane",
        "latitude": 17.9689,
        "longitude": 102.6137
    },
    {
        
        "zoomLevel": 6, "type": "circle",           "width": 0,           "height": 0,
        "alpha": 0.2,
        "rollOverColor": "#fff",
        "rollOverScale": 1,
        "selectedScale": 2,
        "Scale": 0.5,
        "title": "Beyrouth / Beirut",
        "latitude": 33.8872,
        "longitude": 35.5134
    },
    {
        
        "zoomLevel": 6, "type": "circle",           "width": 0,           "height": 0,
        "alpha": 0.2,
        "rollOverColor": "#fff",
        "rollOverScale": 1,
        "selectedScale": 2,
        "Scale": 0.5,
        "title": "Kuala Lumpur",
        "latitude": 3.1502,
        "longitude": 101.7077
    },
    {
        
        "zoomLevel": 6, "type": "circle",           "width": 0,           "height": 0,
        "alpha": 0.2,
        "rollOverColor": "#fff",
        "rollOverScale": 1,
        "selectedScale": 2,
        "Scale": 0.5,
        "title": "Ulan Bator",
        "latitude": 47.9138,
        "longitude": 106.9220
    },
    {
        
        "zoomLevel": 6, "type": "circle",           "width": 0,           "height": 0,
        "alpha": 0.2,
        "rollOverColor": "#fff",
        "rollOverScale": 1,
        "selectedScale": 2,
        "Scale": 0.5,
        "title": "Pyinmana",
        "latitude": 19.7378,
        "longitude": 96.2083
    },
    {
        
        "zoomLevel": 6, "type": "circle",           "width": 0,           "height": 0,
        "alpha": 0.2,
        "rollOverColor": "#fff",
        "rollOverScale": 1,
        "selectedScale": 2,
        "Scale": 0.5,
        "title": "Kathmandu",
        "latitude": 27.7058,
        "longitude": 85.3157
    },
    {
        
        "zoomLevel": 6, "type": "circle",           "width": 0,           "height": 0,
        "alpha": 0.2,
        "rollOverColor": "#fff",
        "rollOverScale": 1,
        "selectedScale": 2,
        "Scale": 0.5,
        "title": "Muscat",
        "latitude": 23.6086,
        "longitude": 58.5922
    },
    {
        
        "zoomLevel": 6, "type": "circle",           "width": 0,           "height": 0,
        "alpha": 0.2,
        "rollOverColor": "#fff",
        "rollOverScale": 1,
        "selectedScale": 2,
        "Scale": 0.5,
        "title": "Islamabad",
        "latitude": 33.6751,
        "longitude": 73.0946
    },
    {
        
        "zoomLevel": 6, "type": "circle",           "width": 0,           "height": 0,
        "alpha": 0.2,
        "rollOverColor": "#fff",
        "rollOverScale": 1,
        "selectedScale": 2,
        "Scale": 0.5,
        "title": "Manila",
        "latitude": 14.5790,
        "longitude": 120.9726
    },
    {
        
        "zoomLevel": 6, "type": "circle",           "width": 0,           "height": 0,
        "alpha": 0.2,
        "rollOverColor": "#fff",
        "rollOverScale": 1,
        "selectedScale": 2,
        "Scale": 0.5,
        "title": "Doha",
        "latitude": 25.2948,
        "longitude": 51.5082
    },
    {
        
        "zoomLevel": 6, "type": "circle",           "width": 0,           "height": 0,
        "alpha": 0.2,
        "rollOverColor": "#fff",
        "rollOverScale": 1,
        "selectedScale": 2,
        "Scale": 0.5,
        "title": "Riyadh",
        "latitude": 24.6748,
        "longitude": 46.6977
    },
    {
        
        "zoomLevel": 6, "type": "circle",           "width": 0,           "height": 0,
        "alpha": 0.2,
        "rollOverColor": "#fff",
        "rollOverScale": 1,
        "selectedScale": 2,
        "Scale": 0.5,
        "title": "Singapore",
        "latitude": 1.2894,
        "longitude": 103.8500
    },
    {
        
        "zoomLevel": 6, "type": "circle",           "width": 0,           "height": 0,
        "alpha": 0.2,
        "rollOverColor": "#fff",
        "rollOverScale": 1,
        "selectedScale": 2,
        "Scale": 0.5,
        "title": "Seoul",
        "latitude": 37.5139,
        "longitude": 126.9828
    },
    {
        
        "zoomLevel": 6, "type": "circle",           "width": 0,           "height": 0,
        "alpha": 0.2,
        "rollOverColor": "#fff",
        "rollOverScale": 1,
        "selectedScale": 2,
        "Scale": 0.5,
        "title": "Colombo",
        "latitude": 6.9155,
        "longitude": 79.8572
    },
    {
        
        "zoomLevel": 6, "type": "circle",           "width": 0,           "height": 0,
        "alpha": 0.2,
        "rollOverColor": "#fff",
        "rollOverScale": 1,
        "selectedScale": 2,
        "Scale": 0.5,
        "title": "Damascus",
        "latitude": 33.5158,
        "longitude": 36.2939
    },
    {
        
        "zoomLevel": 6, "type": "circle",           "width": 0,           "height": 0,
        "alpha": 0.2,
        "rollOverColor": "#fff",
        "rollOverScale": 1,
        "selectedScale": 2,
        "Scale": 0.5,
        "title": "Taipei",
        "latitude": 25.0338,
        "longitude": 121.5645
    },
    {
        
        "zoomLevel": 6, "type": "circle",           "width": 0,           "height": 0,
        "alpha": 0.2,
        "rollOverColor": "#fff",
        "rollOverScale": 1,
        "selectedScale": 2,
        "Scale": 0.5,
        "title": "Dushanbe",
        "latitude": 38.5737,
        "longitude": 68.7738
    },
    {
        
        "zoomLevel": 6, "type": "circle",           "width": 0,           "height": 0,
        "alpha": 0.2,
        "rollOverColor": "#fff",
        "rollOverScale": 1,
        "selectedScale": 2,
        "Scale": 0.5,
        "title": "Bangkok",
        "latitude": 13.7573,
        "longitude": 100.5020
    },
    {
        
        "zoomLevel": 6, "type": "circle",           "width": 0,           "height": 0,
        "alpha": 0.2,
        "rollOverColor": "#fff",
        "rollOverScale": 1,
        "selectedScale": 2,
        "Scale": 0.5,
        "title": "Dili",
        "latitude": -8.5662,
        "longitude": 125.5880
    },
    {
        
        "zoomLevel": 6, "type": "circle",           "width": 0,           "height": 0,
        "alpha": 0.2,
        "rollOverColor": "#fff",
        "rollOverScale": 1,
        "selectedScale": 2,
        "Scale": 0.5,
        "title": "Ankara",
        "latitude": 39.9439,
        "longitude": 32.8560
    },
    {
        
        "zoomLevel": 6, "type": "circle",           "width": 0,           "height": 0,
        "alpha": 0.2,
        "rollOverColor": "#fff",
        "rollOverScale": 1,
        "selectedScale": 2,
        "Scale": 0.5,
        "title": "Ashgabat",
        "latitude": 37.9509,
        "longitude": 58.3794
    },
    {
        
        "zoomLevel": 6, "type": "circle",           "width": 0,           "height": 0,
        "alpha": 0.2,
        "rollOverColor": "#fff",
        "rollOverScale": 1,
        "selectedScale": 2,
        "Scale": 0.5,
        "title": "Abu Dhabi",
        "latitude": 24.4764,
        "longitude": 54.3705
    },
    {
        
        "zoomLevel": 6, "type": "circle",           "width": 0,           "height": 0,
        "alpha": 0.2,
        "rollOverColor": "#fff",
        "rollOverScale": 1,
        "selectedScale": 2,
        "Scale": 0.5,
        "title": "Tashkent",
        "latitude": 41.3193,
        "longitude": 69.2481
    },
    {
        
        "zoomLevel": 6, "type": "circle",           "width": 0,           "height": 0,
        "alpha": 0.2,
        "rollOverColor": "#fff",
        "rollOverScale": 1,
        "selectedScale": 2,
        "Scale": 0.5,
        "title": "Hanoi",
        "latitude": 21.0341,
        "longitude": 105.8372
    },
    {
        
        "zoomLevel": 6, "type": "circle",           "width": 0,           "height": 0,
        "alpha": 0.2,
        "rollOverColor": "#fff",
        "rollOverScale": 1,
        "selectedScale": 2,
        "Scale": 0.5,
        "title": "Sanaa",
        "latitude": 15.3556,
        "longitude": 44.2081
    },
    {
        
        "zoomLevel": 6, "type": "circle",           "width": 0,           "height": 0,
        "alpha": 0.2,
        "rollOverColor": "#fff",
        "rollOverScale": 1,
        "selectedScale": 2,
        "Scale": 0.5,
        "title": "Bridgetown",
        "latitude": 13.0935,
        "longitude": -59.6105
    },
    {
        
        "zoomLevel": 6, "type": "circle",           "width": 0,           "height": 0,
        "alpha": 0.2,
        "rollOverColor": "#fff",
        "rollOverScale": 1,
        "selectedScale": 2,
        "Scale": 0.5,
        "title": "Belmopan",
        "latitude": 17.2534,
        "longitude": -88.7713
    },
    {
        
        "zoomLevel": 6, "type": "circle",           "width": 0,           "height": 0,
        "alpha": 0.2,
        "rollOverColor": "#fff",
        "rollOverScale": 1,
        "selectedScale": 2,
        "Scale": 0.5,
        "title": "Sucre",
        "latitude": -19.0421,
        "longitude": -65.2559
    },
    {
        
        "zoomLevel": 6, "type": "circle",           "width": 0,           "height": 0,
        "alpha": 0.2,
        "rollOverColor": "#fff",
        "rollOverScale": 1,
        "selectedScale": 2,
        "Scale": 0.5,
        "title": "Ottawa",
        "latitude": 45.4235,
        "longitude": -75.6979
    },
    {
        
        "zoomLevel": 6, "type": "circle",           "width": 0,           "height": 0,
        "alpha": 0.2,
        "rollOverColor": "#fff",
        "rollOverScale": 1,
        "selectedScale": 2,
        "Scale": 0.5,
        "title": "Santiago",
        "latitude": -33.4691,
        "longitude": -70.6420
    },
    {
        
        "zoomLevel": 6, "type": "circle",           "width": 0,           "height": 0,
        "alpha": 0.2,
        "rollOverColor": "#fff",
        "rollOverScale": 1,
        "selectedScale": 2,
        "Scale": 0.5,
        "title": "Bogota",
        "latitude": 4.6473,
        "longitude": -74.0962
    },
    {
        
        "zoomLevel": 6, "type": "circle",           "width": 0,           "height": 0,
        "alpha": 0.2,
        "rollOverColor": "#fff",
        "rollOverScale": 1,
        "selectedScale": 2,
        "Scale": 0.5,
        "title": "San Jose",
        "latitude": 9.9402,
        "longitude": -84.1002
    },
    {
        
        "zoomLevel": 6, "type": "circle",           "width": 0,           "height": 0,
        "alpha": 0.2,
        "rollOverColor": "#fff",
        "rollOverScale": 1,
        "selectedScale": 2,
        "Scale": 0.5,
        "title": "Havana",
        "latitude": 23.1333,
        "longitude": -82.3667
    },
    {
        
        "zoomLevel": 6, "type": "circle",           "width": 0,           "height": 0,
        "alpha": 0.2,
        "rollOverColor": "#fff",
        "rollOverScale": 1,
        "selectedScale": 2,
        "Scale": 0.5,
        "title": "Roseau",
        "latitude": 15.2976,
        "longitude": -61.3900
    },
    {
        
        "zoomLevel": 6, "type": "circle",           "width": 0,           "height": 0,
        "alpha": 0.2,
        "rollOverColor": "#fff",
        "rollOverScale": 1,
        "selectedScale": 2,
        "Scale": 0.5,
        "title": "Santo Domingo",
        "latitude": 18.4790,
        "longitude": -69.8908
    },
    {
        
        "zoomLevel": 6, "type": "circle",           "width": 0,           "height": 0,
        "alpha": 0.2,
        "rollOverColor": "#fff",
        "rollOverScale": 1,
        "selectedScale": 2,
        "Scale": 0.5,
        "title": "Quito",
        "latitude": -0.2295,
        "longitude": -78.5243
    },
    {
        
        "zoomLevel": 6, "type": "circle",           "width": 0,           "height": 0,
        "alpha": 0.2,
        "rollOverColor": "#fff",
        "rollOverScale": 1,
        "selectedScale": 2,
        "Scale": 0.5,
        "title": "San Salvador",
        "latitude": 13.7034,
        "longitude": -89.2073
    },
    {
        
        "zoomLevel": 6, "type": "circle",           "width": 0,           "height": 0,
        "alpha": 0.2,
        "rollOverColor": "#fff",
        "rollOverScale": 1,
        "selectedScale": 2,
        "Scale": 0.5,
        "title": "Guatemala",
        "latitude": 14.6248,
        "longitude": -90.5328
    },
    {
        
        "zoomLevel": 6, "type": "circle",           "width": 0,           "height": 0,
        "alpha": 0.2,
        "rollOverColor": "#fff",
        "rollOverScale": 1,
        "selectedScale": 2,
        "Scale": 0.5,
        "title": "Ciudad de Mexico",
        "latitude": 19.4271,
        "longitude": -99.1276
    },
    {
        
        "zoomLevel": 6, "type": "circle",           "width": 0,           "height": 0,
        "alpha": 0.2,
        "rollOverColor": "#fff",
        "rollOverScale": 1,
        "selectedScale": 2,
        "Scale": 0.5,
        "title": "Managua",
        "latitude": 12.1475,
        "longitude": -86.2734
    },
    {
        
        "zoomLevel": 6, "type": "circle",           "width": 0,           "height": 0,
        "alpha": 0.2,
        "rollOverColor": "#fff",
        "rollOverScale": 1,
        "selectedScale": 2,
        "Scale": 0.5,
        "title": "Panama",
        "latitude": 8.9943,
        "longitude": -79.5188
    },
    {
        
        "zoomLevel": 6, "type": "circle",           "width": 0,           "height": 0,
        "alpha": 0.2,
        "rollOverColor": "#fff",
        "rollOverScale": 1,
        "selectedScale": 2,
        "Scale": 0.5,
        "title": "Asuncion",
        "latitude": -25.3005,
        "longitude": -57.6362
    },
    {
        
        "zoomLevel": 6, "type": "circle",           "width": 0,           "height": 0,
        "alpha": 0.2,
        "rollOverColor": "#fff",
        "rollOverScale": 1,
        "selectedScale": 2,
        "Scale": 0.5,
        "title": "Lima",
        "latitude": -12.0931,
        "longitude": -77.0465
    },
    {
        
        "zoomLevel": 6, "type": "circle",           "width": 0,           "height": 0,
        "alpha": 0.2,
        "rollOverColor": "#fff",
        "rollOverScale": 1,
        "selectedScale": 2,
        "Scale": 0.5,
        "title": "Castries",
        "latitude": 13.9972,
        "longitude": -60.0018
    },
    {
        
        "zoomLevel": 6, "type": "circle",           "width": 0,           "height": 0,
        "alpha": 0.2,
        "rollOverColor": "#fff",
        "rollOverScale": 1,
        "selectedScale": 2,
        "Scale": 0.5,
        "title": "Paramaribo",
        "latitude": 5.8232,
        "longitude": -55.1679
    },
    {
        
        "zoomLevel": 6, "type": "circle",           "width": 0,           "height": 0,
        "alpha": 0.2,
        "rollOverColor": "#fff",
        "rollOverScale": 1,
        "selectedScale": 2,
        "Scale": 0.5,
        "title": "Montevideo",
        "latitude": -34.8941,
        "longitude": -56.0675
    },
    {
        
        "zoomLevel": 6, "type": "circle",           "width": 0,           "height": 0,
        "alpha": 0.2,
        "rollOverColor": "#fff",
        "rollOverScale": 1,
        "selectedScale": 2,
        "Scale": 0.5,
        "title": "Caracas",
        "latitude": 10.4961,
        "longitude": -66.8983
    },
    {
        
        "zoomLevel": 6, "type": "circle",           "width": 0,           "height": 0,
        "alpha": 0.2,
        "rollOverColor": "#fff",
        "rollOverScale": 1,
        "selectedScale": 2,
        "Scale": 0.5,
        "title": "Oranjestad",
        "latitude": 12.5246,
        "longitude": -70.0265
    },
    {
        
        "zoomLevel": 6, "type": "circle",           "width": 0,           "height": 0,
        "alpha": 0.2,
        "rollOverColor": "#fff",
        "rollOverScale": 1,
        "selectedScale": 2,
        "Scale": 0.5,
        "title": "Cayenne",
        "latitude": 4.9346,
        "longitude": -52.3303
    },
    {
        
        "zoomLevel": 6, "type": "circle",           "width": 0,           "height": 0,
        "alpha": 0.2,
        "rollOverColor": "#fff",
        "rollOverScale": 1,
        "selectedScale": 2,
        "Scale": 0.5,
        "title": "Plymouth",
        "latitude": 16.6802,
        "longitude": -62.2014
    },
    {
        
        "zoomLevel": 6, "type": "circle",           "width": 0,           "height": 0,
        "alpha": 0.2,
        "rollOverColor": "#fff",
        "rollOverScale": 1,
        "selectedScale": 2,
        "Scale": 0.5,
        "title": "San Juan",
        "latitude": 18.4500,
        "longitude": -66.0667
    },
    {
        
        "zoomLevel": 6, "type": "circle",           "width": 0,           "height": 0,
        "alpha": 0.2,
        "rollOverColor": "#fff",
        "rollOverScale": 1,
        "selectedScale": 2,
        "Scale": 0.5,
        "title": "Algiers",
        "latitude": 36.7755,
        "longitude": 3.0597
    },
    {
        
        "zoomLevel": 6, "type": "circle",           "width": 0,           "height": 0,
        "alpha": 0.2,
        "rollOverColor": "#fff",
        "rollOverScale": 1,
        "selectedScale": 2,
        "Scale": 0.5,
        "title": "Luanda",
        "latitude": -8.8159,
        "longitude": 13.2306
    },
    {
        
        "zoomLevel": 6, "type": "circle",           "width": 0,           "height": 0,
        "alpha": 0.2,
        "rollOverColor": "#fff",
        "rollOverScale": 1,
        "selectedScale": 2,
        "Scale": 0.5,
        "title": "Porto-Novo",
        "latitude": 6.4779,
        "longitude": 2.6323
    },
    {
        
        "zoomLevel": 6, "type": "circle",           "width": 0,           "height": 0,
        "alpha": 0.2,
        "rollOverColor": "#fff",
        "rollOverScale": 1,
        "selectedScale": 2,
        "Scale": 0.5,
        "title": "Gaborone",
        "latitude": -24.6570,
        "longitude": 25.9089
    },
    {
        
        "zoomLevel": 6, "type": "circle",           "width": 0,           "height": 0,
        "alpha": 0.2,
        "rollOverColor": "#fff",
        "rollOverScale": 1,
        "selectedScale": 2,
        "Scale": 0.5,
        "title": "Ouagadougou",
        "latitude": 12.3569,
        "longitude": -1.5352
    },
    {
        
        "zoomLevel": 6, "type": "circle",           "width": 0,           "height": 0,
        "alpha": 0.2,
        "rollOverColor": "#fff",
        "rollOverScale": 1,
        "selectedScale": 2,
        "Scale": 0.5,
        "title": "Bujumbura",
        "latitude": -3.3818,
        "longitude": 29.3622
    },
    {
        
        "zoomLevel": 6, "type": "circle",           "width": 0,           "height": 0,
        "alpha": 0.2,
        "rollOverColor": "#fff",
        "rollOverScale": 1,
        "selectedScale": 2,
        "Scale": 0.5,
        "title": "Yaounde",
        "latitude": 3.8612,
        "longitude": 11.5217
    },
    {
        
        "zoomLevel": 6, "type": "circle",           "width": 0,           "height": 0,
        "alpha": 0.2,
        "rollOverColor": "#fff",
        "rollOverScale": 1,
        "selectedScale": 2,
        "Scale": 0.5,
        "title": "Bangui",
        "latitude": 4.3621,
        "longitude": 18.5873
    },
    {
        
        "zoomLevel": 6, "type": "circle",           "width": 0,           "height": 0,
        "alpha": 0.2,
        "rollOverColor": "#fff",
        "rollOverScale": 1,
        "selectedScale": 2,
        "Scale": 0.5,
        "title": "Brazzaville",
        "latitude": -4.2767,
        "longitude": 15.2662
    },
    {
        
        "zoomLevel": 6, "type": "circle",           "width": 0,           "height": 0,
        "alpha": 0.2,
        "rollOverColor": "#fff",
        "rollOverScale": 1,
        "selectedScale": 2,
        "Scale": 0.5,
        "title": "Kinshasa",
        "latitude": -4.3369,
        "longitude": 15.3271
    },
    {
        
        "zoomLevel": 6, "type": "circle",           "width": 0,           "height": 0,
        "alpha": 0.2,
        "rollOverColor": "#fff",
        "rollOverScale": 1,
        "selectedScale": 2,
        "Scale": 0.5,
        "title": "Yamoussoukro",
        "latitude": 6.8067,
        "longitude": -5.2728
    },
    {
        
        "zoomLevel": 6, "type": "circle",           "width": 0,           "height": 0,
        "alpha": 0.2,
        "rollOverColor": "#fff",
        "rollOverScale": 1,
        "selectedScale": 2,
        "Scale": 0.5,
        "title": "Djibouti",
        "latitude": 11.5806,
        "longitude": 43.1425
    },
    {
        
        "zoomLevel": 6, "type": "circle",           "width": 0,           "height": 0,
        "alpha": 0.2,
        "rollOverColor": "#fff",
        "rollOverScale": 1,
        "selectedScale": 2,
        "Scale": 0.5,
        "title": "Cairo",
        "latitude": 30.0571,
        "longitude": 31.2272
    },
    {
        
        "zoomLevel": 6, "type": "circle",           "width": 0,           "height": 0,
        "alpha": 0.2,
        "rollOverColor": "#fff",
        "rollOverScale": 1,
        "selectedScale": 2,
        "Scale": 0.5,
        "title": "Asmara",
        "latitude": 15.3315,
        "longitude": 38.9183
    },
    {
        
        "zoomLevel": 6, "type": "circle",           "width": 0,           "height": 0,
        "alpha": 0.2,
        "rollOverColor": "#fff",
        "rollOverScale": 1,
        "selectedScale": 2,
        "Scale": 0.5,
        "title": "Addis Abeba",
        "latitude": 9.0084,
        "longitude": 38.7575
    },
    {
        
        "zoomLevel": 6, "type": "circle",           "width": 0,           "height": 0,
        "alpha": 0.2,
        "rollOverColor": "#fff",
        "rollOverScale": 1,
        "selectedScale": 2,
        "Scale": 0.5,
        "title": "Libreville",
        "latitude": 0.3858,
        "longitude": 9.4496
    },
    {
        
        "zoomLevel": 6, "type": "circle",           "width": 0,           "height": 0,
        "alpha": 0.2,
        "rollOverColor": "#fff",
        "rollOverScale": 1,
        "selectedScale": 2,
        "Scale": 0.5,
        "title": "Banjul",
        "latitude": 13.4399,
        "longitude": -16.6775
    },
    {
        
        "zoomLevel": 6, "type": "circle",           "width": 0,           "height": 0,
        "alpha": 0.2,
        "rollOverColor": "#fff",
        "rollOverScale": 1,
        "selectedScale": 2,
        "Scale": 0.5,
        "title": "Accra",
        "latitude": 5.5401,
        "longitude": -0.2074
    },
    {
        
        "zoomLevel": 6, "type": "circle",           "width": 0,           "height": 0,
        "alpha": 0.2,
        "rollOverColor": "#fff",
        "rollOverScale": 1,
        "selectedScale": 2,
        "Scale": 0.5,
        "title": "Conakry",
        "latitude": 9.5370,
        "longitude": -13.6785
    },
    {
        
        "zoomLevel": 6, "type": "circle",           "width": 0,           "height": 0,
        "alpha": 0.2,
        "rollOverColor": "#fff",
        "rollOverScale": 1,
        "selectedScale": 2,
        "Scale": 0.5,
        "title": "Bissau",
        "latitude": 11.8598,
        "longitude": -15.5875
    },
    {
        
        "zoomLevel": 6, "type": "circle",           "width": 0,           "height": 0,
        "alpha": 0.2,
        "rollOverColor": "#fff",
        "rollOverScale": 1,
        "selectedScale": 2,
        "Scale": 0.5,
        "title": "Nairobi",
        "latitude": -1.2762,
        "longitude": 36.7965
    },
    {
        
        "zoomLevel": 6, "type": "circle",           "width": 0,           "height": 0,
        "alpha": 0.2,
        "rollOverColor": "#fff",
        "rollOverScale": 1,
        "selectedScale": 2,
        "Scale": 0.5,
        "title": "Maseru",
        "latitude": -29.2976,
        "longitude": 27.4854
    },
    {
        
        "zoomLevel": 6, "type": "circle",           "width": 0,           "height": 0,
        "alpha": 0.2,
        "rollOverColor": "#fff",
        "rollOverScale": 1,
        "selectedScale": 2,
        "Scale": 0.5,
        "title": "Monrovia",
        "latitude": 6.3106,
        "longitude": -10.8047
    },
    {
        
        "zoomLevel": 6, "type": "circle",           "width": 0,           "height": 0,
        "alpha": 0.2,
        "rollOverColor": "#fff",
        "rollOverScale": 1,
        "selectedScale": 2,
        "Scale": 0.5,
        "title": "Tripoli",
        "latitude": 32.8830,
        "longitude": 13.1897
    },
    {
        
        "zoomLevel": 6, "type": "circle",           "width": 0,           "height": 0,
        "alpha": 0.2,
        "rollOverColor": "#fff",
        "rollOverScale": 1,
        "selectedScale": 2,
        "Scale": 0.5,
        "title": "Antananarivo",
        "latitude": -18.9201,
        "longitude": 47.5237
    },
    {
        
        "zoomLevel": 6, "type": "circle",           "width": 0,           "height": 0,
        "alpha": 0.2,
        "rollOverColor": "#fff",
        "rollOverScale": 1,
        "selectedScale": 2,
        "Scale": 0.5,
        "title": "Lilongwe",
        "latitude": -13.9899,
        "longitude": 33.7703
    },
    {
        
        "zoomLevel": 6, "type": "circle",           "width": 0,           "height": 0,
        "alpha": 0.2,
        "rollOverColor": "#fff",
        "rollOverScale": 1,
        "selectedScale": 2,
        "Scale": 0.5,
        "title": "Bamako",
        "latitude": 12.6530,
        "longitude": -7.9864
    },
    {
        
        "zoomLevel": 6, "type": "circle",           "width": 0,           "height": 0,
        "alpha": 0.2,
        "rollOverColor": "#fff",
        "rollOverScale": 1,
        "selectedScale": 2,
        "Scale": 0.5,
        "title": "Nouakchott",
        "latitude": 18.0669,
        "longitude": -15.9900
    },
    {
        
        "zoomLevel": 6, "type": "circle",           "width": 0,           "height": 0,
        "alpha": 0.2,
        "rollOverColor": "#fff",
        "rollOverScale": 1,
        "selectedScale": 2,
        "Scale": 0.5,
        "title": "Port Louis",
        "latitude": -20.1654,
        "longitude": 57.4896
    },
    {
        
        "zoomLevel": 6, "type": "circle",           "width": 0,           "height": 0,
        "alpha": 0.2,
        "rollOverColor": "#fff",
        "rollOverScale": 1,
        "selectedScale": 2,
        "Scale": 0.5,
        "title": "Rabat",
        "latitude": 33.9905,
        "longitude": -6.8704
    },
    {
        
        "zoomLevel": 6, "type": "circle",           "width": 0,           "height": 0,
        "alpha": 0.2,
        "rollOverColor": "#fff",
        "rollOverScale": 1,
        "selectedScale": 2,
        "Scale": 0.5,
        "title": "Maputo",
        "latitude": -25.9686,
        "longitude": 32.5804
    },
    {
        
        "zoomLevel": 6, "type": "circle",           "width": 0,           "height": 0,
        "alpha": 0.2,
        "rollOverColor": "#fff",
        "rollOverScale": 1,
        "selectedScale": 2,
        "Scale": 0.5,
        "title": "Windhoek",
        "latitude": -22.5749,
        "longitude": 17.0805
    },
    {
        
        "zoomLevel": 6, "type": "circle",           "width": 0,           "height": 0,
        "alpha": 0.2,
        "rollOverColor": "#fff",
        "rollOverScale": 1,
        "selectedScale": 2,
        "Scale": 0.5,
        "title": "Niamey",
        "latitude": 13.5164,
        "longitude": 2.1157
    },
    {
        
        "zoomLevel": 6, "type": "circle",           "width": 0,           "height": 0,
        "alpha": 0.2,
        "rollOverColor": "#fff",
        "rollOverScale": 1,
        "selectedScale": 2,
        "Scale": 0.5,
        "title": "Abuja",
        "latitude": 9.0580,
        "longitude": 7.4891
    },
    {
        
        "zoomLevel": 6, "type": "circle",           "width": 0,           "height": 0,
        "alpha": 0.2,
        "rollOverColor": "#fff",
        "rollOverScale": 1,
        "selectedScale": 2,
        "Scale": 0.5,
        "title": "Kigali",
        "latitude": -1.9441,
        "longitude": 30.0619
    },
    {
        
        "zoomLevel": 6, "type": "circle",           "width": 0,           "height": 0,
        "alpha": 0.2,
        "rollOverColor": "#fff",
        "rollOverScale": 1,
        "selectedScale": 2,
        "Scale": 0.5,
        "title": "Dakar",
        "latitude": 14.6953,
        "longitude": -17.4439
    },
    {
        
        "zoomLevel": 6, "type": "circle",           "width": 0,           "height": 0,
        "alpha": 0.2,
        "rollOverColor": "#fff",
        "rollOverScale": 1,
        "selectedScale": 2,
        "Scale": 0.5,
        "title": "Freetown",
        "latitude": 8.4697,
        "longitude": -13.2659
    },
    {
        
        "zoomLevel": 6, "type": "circle",           "width": 0,           "height": 0,
        "alpha": 0.2,
        "rollOverColor": "#fff",
        "rollOverScale": 1,
        "selectedScale": 2,
        "Scale": 0.5,
        "title": "Mogadishu",
        "latitude": 2.0411,
        "longitude": 45.3426
    },
    {
        
        "zoomLevel": 6, "type": "circle",           "width": 0,           "height": 0,
        "alpha": 0.2,
        "rollOverColor": "#fff",
        "rollOverScale": 1,
        "selectedScale": 2,
        "Scale": 0.5,
        "title": "Pretoria",
        "latitude": -25.7463,
        "longitude": 28.1876
    },
    {
        
        "zoomLevel": 6, "type": "circle",           "width": 0,           "height": 0,
        "alpha": 0.2,
        "rollOverColor": "#fff",
        "rollOverScale": 1,
        "selectedScale": 2,
        "Scale": 0.5,
        "title": "Mbabane",
        "latitude": -26.3186,
        "longitude": 31.1410
    },
    {
        
        "zoomLevel": 6, "type": "circle",           "width": 0,           "height": 0,
        "alpha": 0.2,
        "rollOverColor": "#fff",
        "rollOverScale": 1,
        "selectedScale": 2,
        "Scale": 0.5,
        "title": "Dodoma",
        "latitude": -6.1670,
        "longitude": 35.7497
    },
    {
        
        "zoomLevel": 6, "type": "circle",           "width": 0,           "height": 0,
        "alpha": 0.2,
        "rollOverColor": "#fff",
        "rollOverScale": 1,
        "selectedScale": 2,
        "Scale": 0.5,
        "title": "Lome",
        "latitude": 6.1228,
        "longitude": 1.2255
    },
    {
        
        "zoomLevel": 6, "type": "circle",           "width": 0,           "height": 0,
        "alpha": 0.2,
        "rollOverColor": "#fff",
        "rollOverScale": 1,
        "selectedScale": 2,
        "Scale": 0.5,
        "title": "Tunis",
        "latitude": 36.8117,
        "longitude": 10.1761
    }
  ]
}